{
  "generator-jhipster": {
    "applicationType": "monolith",
    "gitCompany": "",
    "baseName": "jhipsterSampleApplication",
    "packageName": "io.github.jhipster.application",
    "packageFolder": "io/github/jhipster/application",
    "serverPort": 8080,
    "serviceDiscoveryType": false,
    "authenticationType": "jwt",
    "uaaBaseName": "../uaa",
    "cacheProvider": "ehcache",
    "enableHibernateCache": true,
    "websocket": false,
    "databaseType": "sql",
    "devDatabaseType": "h2Disk",
    "prodDatabaseType": "mysql",
    "searchEngine": false,
    "enableSwaggerCodegen": false,
    "messageBroker": false,
    "buildTool": "maven",
    "useSass": false,
    "clientPackageManager": "npm",
    "testFrameworks": [],
    "enableTranslation": false,
    "nativeLanguage": "en",
    "languages": [
      "en"
    ],
    "clientFramework": "angularX",
    "jhiPrefix": "jhi",
    "jhipsterVersion": "5.8.1",
    "jwtSecretKey": "MGMwZDAzYzU3MDgwYTMwZWRlYjBlN2M3M2Y5ZmE0ZGJmMzc1MzAzNDBlOGQ0MjZiYTVkMmMwNWNlNWQzYzdlNDk1MjdmMDhlMjg3ZDQ3ZDYxYjI3MmJhODI3ODNhNmMyZmNiZmE1Njg0ZjdjYjUwYjc1YjFkYTlkMjdhODU4NDk=",
    "entitySuffix": "",
    "dtoSuffix": "DTO",
    "otherModules": []
  },
  "git-provider": "GitHub",
  "git-company": "chrisdns",
  "repository-name": "jhipster-sample-application"
}